lensguild/__init__.py
lensguild/GUI/draw_layout.py
lensguild/GUI/print_layout.py
lensguild/GUI/visual.py
lensguild/filter/__init__.py
lensguild/filter/filter.py
lensguild/filter/filterDB.py
lensguild/objective/Commonlands.py
lensguild/objective/EdmundOptics.py
lensguild/objective/Navitar.py
lensguild/objective/Sunex.py
lensguild/objective/__init__.py
lensguild/objective/objective.py
lensguild/objective/objectivesDB.py
lensguild/optics/__init__.py
lensguild/optics/aperture_type.py
lensguild/optics/field.py
lensguild/optics/lens_data.py
lensguild/optics/material.py
lensguild/optics/materials_catalog.py
lensguild/optics/obj.py
lensguild/optics/paraxial_magnificatoin.py
lensguild/optics/radius.py
lensguild/optics/refractive_index.py
lensguild/optics/surface.py
lensguild/optics/system.py
lensguild/optics/wavelength.py
lensguild/optics/wavelengths.py
lensguild/raytracing/LocalCoordinates.py
lensguild/raytracing/__init__.py
lensguild/raytracing/bundle.py
lensguild/raytracing/direction.py
lensguild/raytracing/epd_position.py
lensguild/raytracing/matrix.py
lensguild/raytracing/paraxial_angle.py
lensguild/raytracing/point.py
lensguild/raytracing/ray.py
lensguild/raytracing/ray_vector.py
lensguild/raytracing/snell_angle.py
lensguild/raytracing/tracing.py
lensguild/wavelength/__init__.py
lensguild/wavelength/optical_wavelength.py
lensguild/wavelength/wavelength.py
lensguild-0.5.1.dist-info/licenses/LICENSE
lensguild-0.5.1.dist-info/METADATA
lensguild-0.5.1.dist-info/WHEEL
lensguild-0.5.1.dist-info/top_level.txt
lensguild-0.5.1.dist-info/RECORD
